odoo/addons/product_packaging_level/README.rst
odoo/addons/product_packaging_level/__init__.py
odoo/addons/product_packaging_level/__manifest__.py
odoo/addons/product_packaging_level/hooks.py
odoo/addons/product_packaging_level/data/product_packaging_level.xml
odoo/addons/product_packaging_level/i18n/ca.po
odoo/addons/product_packaging_level/i18n/es.po
odoo/addons/product_packaging_level/i18n/it.po
odoo/addons/product_packaging_level/i18n/nl.po
odoo/addons/product_packaging_level/i18n/product_packaging_level.pot
odoo/addons/product_packaging_level/models/__init__.py
odoo/addons/product_packaging_level/models/product_packaging.py
odoo/addons/product_packaging_level/models/product_packaging_level.py
odoo/addons/product_packaging_level/models/stock_package_type.py
odoo/addons/product_packaging_level/readme/CONTRIBUTORS.md
odoo/addons/product_packaging_level/readme/CREDITS.md
odoo/addons/product_packaging_level/readme/DESCRIPTION.md
odoo/addons/product_packaging_level/readme/USAGE.md
odoo/addons/product_packaging_level/security/ir.model.access.csv
odoo/addons/product_packaging_level/static/description/icon.png
odoo/addons/product_packaging_level/static/description/index.html
odoo/addons/product_packaging_level/tests/__init__.py
odoo/addons/product_packaging_level/tests/test_product_packaging_level.py
odoo/addons/product_packaging_level/views/product_packaging_level_view.xml
odoo/addons/product_packaging_level/views/product_packaging_view.xml
odoo/addons/product_packaging_level/views/stock_package_type_view.xml
odoo_addon_product_packaging_level-18.0.1.1.0.dist-info/METADATA
odoo_addon_product_packaging_level-18.0.1.1.0.dist-info/WHEEL
odoo_addon_product_packaging_level-18.0.1.1.0.dist-info/top_level.txt
odoo_addon_product_packaging_level-18.0.1.1.0.dist-info/RECORD
